{
  "id": "skilltree:new_skill_47am",
  "bonuses": [
    {
      "type": "skilltree:attribute",
      "attribute": "attributeslib:arrow_damage",
      "id": "bf084f96-741c-454b-afd6-20e39c56fe6b",
      "name": "Skill",
      "amount": 1.0,
      "operation": 0,
      "player_multiplier": {
        "type": "skilltree:none"
      },
      "player_condition": {
        "type": "skilltree:none"
      }
    }
  ],
  "directConnections": [],
  "longConnections": [],
  "oneWayConnections": [],
  "tags": [],
  "backgroundTexture": "skilltree:textures/icons/background/lesser.png",
  "iconTexture": "skilltree:textures/icons/hunter_crafting_notable_1.png",
  "borderTexture": "skilltree:textures/tooltip/lesser.png",
  "positionX": 2059.1846,
  "positionY": 680.6282,
  "buttonSize": 16,
  "isStartingPoint": false
}